xjetsync/__init__.py
xjetsync/api.py
xjetsync/constants.py
syncxjetswap-24.2.23.dist-info/LICENSE
syncxjetswap-24.2.23.dist-info/METADATA
syncxjetswap-24.2.23.dist-info/WHEEL
syncxjetswap-24.2.23.dist-info/top_level.txt
syncxjetswap-24.2.23.dist-info/RECORD
