Metadata-Version: 2.1
Name: syncxjetswap
Version: 24.2.23
Summary: xJetSwap sdk, but not async
Author: Sovenok-Hacker
License: GNU GENERAL PUBLIC LICENSE
Project-URL: Homepage, https://github.com/Sovenok-Hacker/syncxJetConnect
Keywords: TON,blockchain,telegram,cryptocurrency
Classifier: Programming Language :: Python :: 3
Classifier: License :: OSI Approved :: MIT License
Classifier: Operating System :: OS Independent
Requires-Python: >=3.8
License-File: LICENSE
Requires-Dist: httpx
Requires-Dist: ecdsa
